{"status":"ok","message-type":"work","message-version":"1.0.0","message":{"indexed":{"date-parts":[[2019,4,12]],"date-time":"2019-04-12T04:03:24Z","timestamp":1555041804817},"reference-count":35,"publisher":"Springer Nature","issue":"1","license":[{"URL":"http:\/\/www.springer.com\/tdm","start":{"date-parts":[[2015,10,1]],"date-time":"2015-10-01T00:00:00Z","timestamp":1443657600000},"delay-in-days":0,"content-version":"unspecified"}],"content-domain":{"domain":["link.springer.com"],"crossmark-restriction":false},"short-container-title":["BMC Med"],"published-print":{"date-parts":[[2015,12]]},"DOI":"10.1186\/s12916-015-0469-2","type":"journal-article","created":{"date-parts":[[2015,10,1]],"date-time":"2015-10-01T17:13:15Z","timestamp":1443719595000},"update-policy":"http:\/\/dx.doi.org\/10.1007\/springer_crossmark_policy","source":"Crossref","is-referenced-by-count":160,"title":["\u2018Predatory\u2019 open access: a longitudinal study of article volumes and market characteristics"],"prefix":"10.1186","volume":"13","author":[{"given":"Cenyu","family":"Shen","sequence":"first","affiliation":[]},{"given":"Bo-Christer","family":"Bj\u00f6rk","sequence":"additional","affiliation":[]}],"member":"297","published-online":{"date-parts":[[2015,10,1]]},"reference":[{"key":"469_CR1","author":"C Tenopir","year":"2000","unstructured":"Tenopir C, King D. Towards electronic journals: realities for scientists, librarians and publishers. Washington, DC: SLA Publishing; 2000.","volume-title":"Towards electronic journals: realities for scientists, librarians and publishers"},{"key":"469_CR2","author":"P Suber","year":"2012","unstructured":"Suber P. Open access. Boston, MA: MIT Press; 2012.","volume-title":"Open access"},{"key":"469_CR3","doi-asserted-by":"publisher","first-page":"1496","DOI":"10.1002\/asi.22709","volume":"63","author":"B-C Bj\u00f6rk","year":"2012","unstructured":"Bj\u00f6rk B-C. The hybrid model for open access publication of scholarly articles \u2013 a failed experiment? JASIST. 2012;63:1496\u2013504.","journal-title":"JASIST."},{"key":"469_CR4","doi-asserted-by":"publisher","first-page":"310","DOI":"10.1080\/00987913.2004.10764930","volume":"30","author":"S Harnad","year":"2004","unstructured":"Harnad S, Brody T, Vallieres F, Carr L, Hitchcock S, Gingras Y, et al. The access\/impact problem and the green and gold roads to open access. Ser Rev. 2004;30:310\u20134.","journal-title":"Ser Rev."},{"key":"469_CR5","unstructured":"Binfield P. Open access megajournals \u2013 have they changed everything? Wellington: Creative Commons; 2013. http:\/\/creativecommons.org.nz\/2013\/10\/open-access-megajournals-have-they-changed-everything ."},{"key":"469_CR6","doi-asserted-by":"publisher","first-page":"179","DOI":"10.1038\/489179a","volume":"489","author":"J Beall","year":"2012","unstructured":"Beall J. Predatory publishers are corrupting open access. Nature. 2012;489:179\u20139.","journal-title":"Nature."},{"key":"469_CR7","unstructured":"McGlynn T. The evolution of pseudojournals. Dominguez Hills, CA: Small Pond Science; 2013. http:\/\/smallpondscience.com\/2013\/02\/14\/the-evolution-of-pseudojournals ."},{"key":"469_CR8","unstructured":"Beall J. Criteria for determining predatory open-access publishers. 2nd edition. Denver, CO: Scholarly Open Access; 2012. http:\/\/scholarlyoa.files.wordpress.com\/2012\/11\/criteria-2012-2.pdf ."},{"key":"469_CR9","unstructured":"Clarke J, Smith R. Firm action needed on predatory journals. BMJ. 2015;350. doi: http:\/\/dx.doi.org\/10.1136\/bmj.h210 .","DOI":"10.1136\/bmj.h210","doi-asserted-by":"crossref"},{"key":"469_CR10","unstructured":"J\u00e4rvi U. Open access attracts swindlers and idealists. Finnish Med J. 2012. http:\/\/www.laakarilehti.fi\/uutinen.html?opcode=show\/news_id=11711\/type=1 ."},{"key":"469_CR11","unstructured":"Davis P. Open access publisher accepts nonsense manuscript for dollars. The Scholarly Kitchen; 2009. http:\/\/scholarlykitchen.sspnet.org\/2009\/06\/10\/nonsense-for-dollars ."},{"key":"469_CR12","doi-asserted-by":"publisher","first-page":"60","DOI":"10.1126\/science.342.6154.60","volume":"342","author":"J Bohannon","year":"2013","unstructured":"Bohannon J. Who\u2019s afraid of peer review. Science. 2013;342:60\u20135.","journal-title":"Science."},{"key":"469_CR13","doi-asserted-by":"publisher","first-page":"183","DOI":"10.1007\/s11948-014-9521-4","volume":"21","author":"D Djuric","year":"2015","unstructured":"Djuric D. Penetrating the omerta of predatory publishing: the romanian connection. Sci Eng Ethics. 2015;21:183\u2013202.","journal-title":"Sci Eng Ethics."},{"key":"469_CR14","first-page":"69","volume":"18","author":"T Luki\u0107","year":"2014","unstructured":"Luki\u0107 T, Ble\u0161i\u0107 I, Basarin B, Ivanovi\u0107 B, Milo\u0161evi\u0107 D, Sakulski D. Predatory and fake scientific journals\/publishers \u2013 a global outbreak with rising trend: a review. Geographica Pannonica. 2014;18:69\u201381.","journal-title":"Geographica Pannonica."},{"key":"469_CR15","unstructured":"Spears T. Respectable medical journal turns to dark side. Ottawa, ON: Ottawa Citizen; 2014. http:\/\/ottawacitizen.com\/technology\/science\/respected-medical-journal-turns-to-dark-side ."},{"key":"469_CR16","doi-asserted-by":"publisher","first-page":"666","DOI":"10.1177\/0011392113508127","volume":"62","author":"A Omobowale","year":"2014","unstructured":"Omobowale A, Akanle A, Adeniran I, Olayinka K. Peripheral scholarship and the context of foreign paid publishing in Nigeria. Current Sociol. 2014;62:666\u201384. doi: 10.1177\/0011392113508127 .","journal-title":"Current Sociol."},{"key":"469_CR17","doi-asserted-by":"publisher","first-page":"69","DOI":"10.1087\/20150111","volume":"28","author":"J Xia","year":"2015","unstructured":"Xia J. Predatory journals and their article publishing charges. Learned Publishing. 2015;28:69.","journal-title":"Learned Publishing."},{"key":"469_CR18","author":"J Xia","year":"2014","unstructured":"Xia J, Harmon J, Connolly K, Donnelly R, Anderson M, Howard H. Who publishes in predatory journals. JASIST. 2014. doi: 10.1002\/asi.23265 .","journal-title":"JASIST","DOI":"10.1002\/asi.23265","doi-asserted-by":"publisher"},{"key":"469_CR19","doi-asserted-by":"publisher","first-page":"23","DOI":"10.1087\/20150105","volume":"28","author":"W Ezinwa Nwagwu","year":"2015","unstructured":"Ezinwa Nwagwu W, Ojemeni O. Penetration of Nigerian predatory biomedical open access journals 2007-2012: a bibiliometric study. Learned Publishing. 2015;28:23\u201334.","journal-title":"Learned Publishing."},{"key":"469_CR20","unstructured":"Beall J. Beall\u2019s list: potential, possible, or probable predatory scholarly open-access publishers. Denver, CO: Scholarly Open Access; 2013. http:\/\/scholarlyoa.com\/publishers ."},{"key":"469_CR21","author":"S Lohr","year":"2010","edition":"2","unstructured":"Lohr S. Sampling: design and analysis. 2nd ed. Farmington Hills, MI: Cengage Learning; 2010.","volume-title":"Sampling: design and analysis"},{"key":"469_CR22","doi-asserted-by":"publisher","first-page":"124","DOI":"10.1186\/1741-7015-10-124","volume":"10","author":"M Laakso","year":"2012","unstructured":"Laakso M, Bj\u00f6rk B-C. Anatomy of open access publishing - a study of longitudinal development and internal structure. BMC Med. 2012;10:124. doi: 10.1186\/1741-7015-10-124 .","journal-title":"BMC Med."},{"key":"469_CR23","doi-asserted-by":"publisher","first-page":"e20961","DOI":"10.1371\/journal.pone.0020961","volume":"6","author":"M Laakso","year":"2011","unstructured":"Laakso M, Welling P, Bukvova H, Nyman L, Bj\u00f6rk B-C, Hedlund T. The development of open access journal publishing from 1993 to 2009. PLoS One. 2011;6:e20961. doi: 10.1371\/journal.pone.0020961 .","journal-title":"PLoS One."},{"key":"469_CR24","unstructured":"Currency Converter. http:\/\/www.currencyconverterrate.com ."},{"key":"469_CR25","unstructured":"Bj\u00f6rk B-C, Roos A, Lauri M. Scientific journal publishing: yearly volume and open access availability. Information Research: An International Electronic Journal. 2009;14. http:\/\/www.informationr.net\/ir\/14-1\/paper391.html ."},{"key":"469_CR26","doi-asserted-by":"publisher","first-page":"1485","DOI":"10.1002\/asi.22673","volume":"63","author":"D Solomon","year":"2012","unstructured":"Solomon D, Bj\u00f6rk B-C. A study of open access journals using article processing charges. JASIST. 2012;63:1485\u201395.","journal-title":"JASIST."},{"key":"469_CR27","doi-asserted-by":"publisher","first-page":"1","DOI":"10.3390\/publications3010001","volume":"3","author":"H Morrison","year":"2015","unstructured":"Morrison H, Salhab J, Calv\u00e9-Genest A, Horava T. Open access article processing charges: DOAJ survey May 2014. Publications. 2015;3:1\u201316. doi: 10.3390\/publications3010001 .","journal-title":"Publications."},{"key":"469_CR28","unstructured":"Schimmer R, Geschuhn K, Vogler A. Disrutping the subscription journals\u2019 business model for the necessary large-scale transformation to open access. Max Planck Digital Library. 2015. doi:10.17617\/1.3."},{"key":"469_CR29","unstructured":"Outsell: open access. Market size, share, forecast, and trends. 2013. http:\/\/goto.copyright.com\/LP=123?source=rightscentral ."},{"key":"469_CR30","unstructured":"Esposito P. The size of the open access market. The Scholarly Kitchen; 2014. http:\/\/scholarlykitchen.sspnet.org\/2014\/10\/29\/the-size-of-the-open-access-market ."},{"key":"469_CR31","doi-asserted-by":"publisher","first-page":"98","DOI":"10.1002\/asi.21660","volume":"63","author":"D Solomon","year":"2012","unstructured":"Solomon D, Bj\u00f6rk B-C. Publication fees in open access publishing: sources of funding and factors influencing choice of journal. JASIST. 2012;63:98\u2013107. doi: 10.1002\/asi.21660 .","journal-title":"JASIST."},{"key":"469_CR32","doi-asserted-by":"publisher","first-page":"914","DOI":"10.1016\/j.joi.2013.09.001","volume":"7","author":"B-C Bj\u00f6rk","year":"2013","unstructured":"Bj\u00f6rk B-C, Solomon D. The publishing delay in scholarly peer-reviewed journals. J Informetrics. 2013;7:914\u201323.","journal-title":"J Informetrics."},{"key":"469_CR33","first-page":"740","volume":"107","author":"R Raghavan","year":"2014","unstructured":"Raghavan R, Dahanukar N, Knight JDM, Bijukumar A, Katwate U, Krishnakumar K, et al. Predatory journals and Indian ichthyology. Current Sci. 2014;107:740\u20132.","journal-title":"Current Sci."},{"key":"469_CR34","doi-asserted-by":"publisher","first-page":"433","DOI":"10.1038\/495433a","volume":"495","author":"D Butler","year":"2013","unstructured":"Butler D. Investigating journals: the dark side of publishing. Nature. 2013;495:433\u20135. doi: 10.1038\/495433a .","journal-title":"Nature."},{"key":"469_CR35","doi-asserted-by":"publisher","first-page":"17","DOI":"10.1038\/512017a","volume":"512","author":"R Noorden Van","year":"2014","unstructured":"Van Noorden R. Open-access website gets tough. Nat News. 2014;512:17.","journal-title":"Nat News."}],"container-title":["BMC Medicine"],"original-title":[],"language":"en","link":[{"URL":"http:\/\/link.springer.com\/content\/pdf\/10.1186\/s12916-015-0469-2.pdf","content-type":"application\/pdf","content-version":"vor","intended-application":"text-mining"},{"URL":"http:\/\/link.springer.com\/article\/10.1186\/s12916-015-0469-2\/fulltext.html","content-type":"text\/html","content-version":"vor","intended-application":"text-mining"},{"URL":"http:\/\/link.springer.com\/content\/pdf\/10.1186\/s12916-015-0469-2.pdf","content-type":"application\/pdf","content-version":"vor","intended-application":"similarity-checking"}],"deposited":{"date-parts":[[2017,6,23]],"date-time":"2017-06-23T20:35:44Z","timestamp":1498250144000},"score":1.0,"subtitle":[],"short-title":[],"issued":{"date-parts":[[2015,10,1]]},"references-count":35,"journal-issue":{"published-print":{"date-parts":[[2015,12]]},"issue":"1"},"alternative-id":["469"],"URL":"http:\/\/dx.doi.org\/10.1186\/s12916-015-0469-2","relation":{"cites":[]},"ISSN":["1741-7015"],"issn-type":[{"value":"1741-7015","type":"electronic"}],"article-number":"230"}}